{
    "type": "DefineShape",
    "id": 1767,
    "bounds": {
        "xMin": -232,
        "xMax": 207,
        "yMin": 49,
        "yMax": 368
    },
    "hasScalingStrokes": false,
    "hasNonScalingStrokes": false,
    "hasFillWinding": false,
    "shape": {
        "initialStyles": {
            "fill": [
                {
                    "type": 4,
                    "color": {
                        "r": 153,
                        "g": 0,
                        "b": 0,
                        "a": 255
                    }
                },
                {
                    "type": 4,
                    "color": {
                        "r": 255,
                        "g": 0,
                        "b": 0,
                        "a": 255
                    }
                },
                {
                    "type": 4,
                    "color": {
                        "r": 101,
                        "g": 1,
                        "b": 1,
                        "a": 255
                    }
                }
            ],
            "line": []
        },
        "records": [
            {
                "type": 1,
                "moveTo": {
                    "x": 66,
                    "y": 166
                },
                "leftFill": 2
            },
            {
                "type": 0,
                "delta": {
                    "x": 8,
                    "y": -5
                }
            },
            {
                "type": 0,
                "delta": {
                    "x": 6,
                    "y": -14
                }
            },
            {
                "type": 0,
                "delta": {
                    "x": 0,
                    "y": -9
                }
            },
            {
                "type": 0,
                "delta": {
                    "x": -29,
                    "y": -24
                }
            },
            {
                "type": 0,
                "delta": {
                    "x": -42,
                    "y": 21
                }
            },
            {
                "type": 0,
                "delta": {
                    "x": 8,
                    "y": 28
                }
            },
            {
                "type": 1,
                "rightFill": 1
            },
            {
                "type": 0,
                "delta": {
                    "x": 49,
                    "y": 3
                }
            },
            {
                "type": 1,
                "leftFill": 0
            },
            {
                "type": 0,
                "delta": {
                    "x": -14,
                    "y": 30
                }
            },
            {
                "type": 0,
                "delta": {
                    "x": -16,
                    "y": 6
                }
            },
            {
                "type": 0,
                "delta": {
                    "x": -22,
                    "y": -29
                }
            },
            {
                "type": 0,
                "delta": {
                    "x": 3,
                    "y": -10
                }
            },
            {
                "type": 1,
                "moveTo": {
                    "x": 159,
                    "y": 292
                },
                "leftFill": 2
            },
            {
                "type": 0,
                "delta": {
                    "x": 21,
                    "y": 13
                }
            },
            {
                "type": 0,
                "delta": {
                    "x": 5,
                    "y": 7
                }
            },
            {
                "type": 0,
                "delta": {
                    "x": 4,
                    "y": 6
                }
            },
            {
                "type": 1,
                "rightFill": 0
            },
            {
                "type": 0,
                "delta": {
                    "x": 12,
                    "y": 18
                }
            },
            {
                "type": 0,
                "delta": {
                    "x": 6,
                    "y": -17
                }
            },
            {
                "type": 0,
                "controlDelta": {
                    "x": -1,
                    "y": -33
                },
                "delta": {
                    "x": -26,
                    "y": -59
                }
            },
            {
                "type": 0,
                "delta": {
                    "x": -6,
                    "y": 1
                }
            },
            {
                "type": 0,
                "delta": {
                    "x": -21,
                    "y": 18
                }
            },
            {
                "type": 0,
                "delta": {
                    "x": 5,
                    "y": 13
                }
            },
            {
                "type": 1,
                "leftFill": 1
            },
            {
                "type": 0,
                "delta": {
                    "x": -2,
                    "y": 23
                }
            },
            {
                "type": 0,
                "delta": {
                    "x": 11,
                    "y": 16
                }
            },
            {
                "type": 0,
                "controlDelta": {
                    "x": 13,
                    "y": 13
                },
                "delta": {
                    "x": 33,
                    "y": 6
                }
            },
            {
                "type": 0,
                "delta": {
                    "x": -12,
                    "y": -19
                }
            },
            {
                "type": 1,
                "moveTo": {
                    "x": 40,
                    "y": 290
                },
                "leftFill": 0,
                "rightFill": 2
            },
            {
                "type": 0,
                "delta": {
                    "x": -8,
                    "y": -4
                }
            },
            {
                "type": 0,
                "delta": {
                    "x": -4,
                    "y": -10
                }
            },
            {
                "type": 0,
                "delta": {
                    "x": 25,
                    "y": -23
                }
            },
            {
                "type": 0,
                "controlDelta": {
                    "x": 64,
                    "y": 16
                },
                "delta": {
                    "x": 69,
                    "y": 81
                }
            },
            {
                "type": 0,
                "delta": {
                    "x": -3,
                    "y": 21
                }
            },
            {
                "type": 0,
                "delta": {
                    "x": -8,
                    "y": 6
                }
            },
            {
                "type": 1,
                "rightFill": 1
            },
            {
                "type": 0,
                "controlDelta": {
                    "x": -40,
                    "y": 2
                },
                "delta": {
                    "x": -55,
                    "y": -24
                }
            },
            {
                "type": 1,
                "rightFill": 2
            },
            {
                "type": 0,
                "delta": {
                    "x": -1,
                    "y": 2
                }
            },
            {
                "type": 0,
                "delta": {
                    "x": -7,
                    "y": 5
                }
            },
            {
                "type": 1,
                "rightFill": 1
            },
            {
                "type": 0,
                "delta": {
                    "x": -1,
                    "y": 12
                }
            },
            {
                "type": 0,
                "delta": {
                    "x": -14,
                    "y": 12
                }
            },
            {
                "type": 0,
                "delta": {
                    "x": -22,
                    "y": -28
                }
            },
            {
                "type": 0,
                "delta": {
                    "x": -2,
                    "y": 10
                }
            },
            {
                "type": 0,
                "delta": {
                    "x": -8,
                    "y": 8
                }
            },
            {
                "type": 0,
                "delta": {
                    "x": -17,
                    "y": -11
                }
            },
            {
                "type": 0,
                "delta": {
                    "x": -12,
                    "y": -31
                }
            },
            {
                "type": 0,
                "delta": {
                    "x": -33,
                    "y": -21
                }
            },
            {
                "type": 1,
                "rightFill": 3
            },
            {
                "type": 0,
                "delta": {
                    "x": -19,
                    "y": 4
                }
            },
            {
                "type": 0,
                "delta": {
                    "x": -10,
                    "y": -12
                }
            },
            {
                "type": 1,
                "rightFill": 1
            },
            {
                "type": 0,
                "delta": {
                    "x": -6,
                    "y": -7
                }
            },
            {
                "type": 0,
                "delta": {
                    "x": -49,
                    "y": 29
                }
            },
            {
                "type": 0,
                "delta": {
                    "x": -25,
                    "y": -29
                }
            },
            {
                "type": 1,
                "rightFill": 2
            },
            {
                "type": 0,
                "delta": {
                    "x": 1,
                    "y": -15
                }
            },
            {
                "type": 1,
                "rightFill": 1
            },
            {
                "type": 0,
                "delta": {
                    "x": -13,
                    "y": -6
                }
            },
            {
                "type": 0,
                "delta": {
                    "x": -5,
                    "y": -6
                }
            },
            {
                "type": 0,
                "delta": {
                    "x": -1,
                    "y": -4
                }
            },
            {
                "type": 0,
                "delta": {
                    "x": -9,
                    "y": -6
                }
            },
            {
                "type": 0,
                "delta": {
                    "x": -6,
                    "y": -16
                }
            },
            {
                "type": 0,
                "delta": {
                    "x": -29,
                    "y": -5
                }
            },
            {
                "type": 0,
                "delta": {
                    "x": 44,
                    "y": -32
                }
            },
            {
                "type": 0,
                "controlDelta": {
                    "x": 25,
                    "y": -4
                },
                "delta": {
                    "x": 15,
                    "y": 20
                }
            },
            {
                "type": 0,
                "delta": {
                    "x": -3,
                    "y": 23
                }
            },
            {
                "type": 0,
                "controlDelta": {
                    "x": 24,
                    "y": -1
                },
                "delta": {
                    "x": 45,
                    "y": 13
                }
            },
            {
                "type": 0,
                "delta": {
                    "x": 30,
                    "y": -32
                }
            },
            {
                "type": 0,
                "delta": {
                    "x": 14,
                    "y": 8
                }
            },
            {
                "type": 1,
                "rightFill": 3
            },
            {
                "type": 0,
                "delta": {
                    "x": 35,
                    "y": 24
                }
            },
            {
                "type": 0,
                "delta": {
                    "x": 3,
                    "y": 17
                }
            },
            {
                "type": 0,
                "delta": {
                    "x": -1,
                    "y": 1
                }
            },
            {
                "type": 1,
                "rightFill": 1
            },
            {
                "type": 0,
                "delta": {
                    "x": 11,
                    "y": -7
                }
            },
            {
                "type": 1,
                "rightFill": 2
            },
            {
                "type": 0,
                "delta": {
                    "x": 3,
                    "y": -8
                }
            },
            {
                "type": 0,
                "delta": {
                    "x": 58,
                    "y": 37
                }
            },
            {
                "type": 0,
                "delta": {
                    "x": 6,
                    "y": 14
                }
            },
            {
                "type": 0,
                "delta": {
                    "x": 15,
                    "y": 7
                }
            },
            {
                "type": 1,
                "rightFill": 1
            },
            {
                "type": 0,
                "delta": {
                    "x": -3,
                    "y": -17
                }
            },
            {
                "type": 1,
                "leftFill": 2
            },
            {
                "type": 0,
                "delta": {
                    "x": 17,
                    "y": -3
                }
            },
            {
                "type": 0,
                "delta": {
                    "x": 54,
                    "y": 74
                }
            },
            {
                "type": 1,
                "moveTo": {
                    "x": -39,
                    "y": 257
                }
            },
            {
                "type": 0,
                "delta": {
                    "x": -3,
                    "y": 12
                }
            },
            {
                "type": 0,
                "controlDelta": {
                    "x": 48,
                    "y": 26
                },
                "delta": {
                    "x": 76,
                    "y": 71
                }
            },
            {
                "type": 0,
                "delta": {
                    "x": 14,
                    "y": 4
                }
            },
            {
                "type": 1,
                "moveTo": {
                    "x": 43,
                    "y": 307
                },
                "leftFill": 1,
                "rightFill": 2
            },
            {
                "type": 0,
                "delta": {
                    "x": 16,
                    "y": 7
                }
            },
            {
                "type": 0,
                "delta": {
                    "x": -3,
                    "y": 23
                }
            },
            {
                "type": 1,
                "moveTo": {
                    "x": -216,
                    "y": 88
                },
                "leftFill": 2,
                "rightFill": 1
            },
            {
                "type": 0,
                "controlDelta": {
                    "x": 11,
                    "y": 5
                },
                "delta": {
                    "x": 21,
                    "y": -5
                }
            },
            {
                "type": 0,
                "delta": {
                    "x": 4,
                    "y": -4
                }
            },
            {
                "type": 0,
                "delta": {
                    "x": 22,
                    "y": 17
                }
            },
            {
                "type": 0,
                "delta": {
                    "x": 14,
                    "y": 3
                }
            },
            {
                "type": 1,
                "rightFill": 0
            },
            {
                "type": 0,
                "delta": {
                    "x": -7,
                    "y": -42
                }
            },
            {
                "type": 0,
                "delta": {
                    "x": -7,
                    "y": -6
                }
            },
            {
                "type": 0,
                "delta": {
                    "x": -17,
                    "y": -2
                }
            },
            {
                "type": 0,
                "delta": {
                    "x": -30,
                    "y": 18
                }
            },
            {
                "type": 0,
                "delta": {
                    "x": 0,
                    "y": 21
                }
            },
            {
                "type": 1,
                "leftFill": 1
            },
            {
                "type": 0,
                "delta": {
                    "x": 3,
                    "y": 16
                }
            },
            {
                "type": 0,
                "delta": {
                    "x": 8,
                    "y": 9
                }
            },
            {
                "type": 0,
                "delta": {
                    "x": 29,
                    "y": 4
                }
            },
            {
                "type": 0,
                "delta": {
                    "x": 10,
                    "y": 14
                }
            },
            {
                "type": 0,
                "delta": {
                    "x": 11,
                    "y": -32
                }
            },
            {
                "type": 1,
                "moveTo": {
                    "x": -50,
                    "y": 264
                },
                "rightFill": 3
            },
            {
                "type": 0,
                "delta": {
                    "x": -11,
                    "y": 31
                }
            },
            {
                "type": 1,
                "moveTo": {
                    "x": -170,
                    "y": 280
                },
                "leftFill": 2,
                "rightFill": 1
            },
            {
                "type": 0,
                "delta": {
                    "x": 13,
                    "y": 11
                }
            },
            {
                "type": 0,
                "delta": {
                    "x": 18,
                    "y": -23
                }
            },
            {
                "type": 0,
                "delta": {
                    "x": -21,
                    "y": -15
                }
            },
            {
                "type": 0,
                "delta": {
                    "x": -9,
                    "y": 12
                }
            },
            {
                "type": 1,
                "moveTo": {
                    "x": -87,
                    "y": 222
                },
                "leftFill": 3
            },
            {
                "type": 0,
                "delta": {
                    "x": -3,
                    "y": 65
                }
            }
        ]
    }
}